README.md
setup.cfg
setup.py
shoelaces/__init__.py
shoelaces/changepoint_analysis.py
shoelaces/dataprocessing.py
shoelaces/graphdockwidget.py
shoelaces/helperwidgets.py
shoelaces/helperwidgets_original.py
shoelaces/main.py
shoelaces/mainwindow.py
shoelaces/offsetwindow.py
shoelaces/readProcessing.py
shoelaces/resource.py
shoelaces/settings.py
shoelaces.egg-info/PKG-INFO
shoelaces.egg-info/SOURCES.txt
shoelaces.egg-info/dependency_links.txt
shoelaces.egg-info/entry_points.txt
shoelaces.egg-info/requires.txt
shoelaces.egg-info/top_level.txt
shoelaces/resources/logo.png
shoelaces/resources/save-icon.png