Metadata-Version: 1.1
Name: shoelaces
Version: 1.5
Summary: An open source program for processsing ribosome profiling data
Home-page: https://bitbucket.org/valenlab/shoelaces
Author: Åsmund Birkeland
Author-email: asmund.birkeland@uib.no
License: UNKNOWN
Download-URL: https://bitbucket.org/valenlab/shoelaces/archive/1.1.tar.gz
Keywords: python,bioinformatics,gui,ribosome profiling
Platform: UNKNOWN
